MANIFEST.in
README.md
mendelianerror.py
setup.py
mendelianerror.egg-info/PKG-INFO
mendelianerror.egg-info/SOURCES.txt
mendelianerror.egg-info/dependency_links.txt
mendelianerror.egg-info/entry_points.txt
mendelianerror.egg-info/not-zip-safe
mendelianerror.egg-info/top_level.txt