Metadata-Version: 1.1
Name: mendelianerror
Version: 0.0.2
Summary: probability of mendelian error in trios
Home-page: UNKNOWN
Author: Brent Pedersen
Author-email: bpederse@gmail.com
License: UNKNOWN
Platform: UNKNOWN
Classifier: Development Status :: 4 - Beta
Classifier: Intended Audience :: Science/Research
Classifier: License :: OSI Approved :: MIT License
Classifier: Topic :: Scientific/Engineering :: Bio-Informatics
